greenenv/__init__.py
greenenv/greenenv.py
greenenv-0.0.3.dist-info/DESCRIPTION.rst
greenenv-0.0.3.dist-info/METADATA
greenenv-0.0.3.dist-info/RECORD
greenenv-0.0.3.dist-info/WHEEL
greenenv-0.0.3.dist-info/metadata.json
greenenv-0.0.3.dist-info/top_level.txt
greenenv-0.0.3.dist-info/zip-safe
with_venv/__init__.py
with_venv/with_venv.py
