Metadata-Version: 2.0
Name: greenenv
Version: 0.0.3
Summary: Context manager controls venv allowing functions to be run in a different interpreter.
Home-page: https://github.com/agodbehere/with-venv
Author: Andrew B Godbehere
Author-email: andrew.godbehere@sumupanalytics.com
License: ISCL
Keywords: greenenv
Platform: UNKNOWN
Classifier: Development Status :: 3 - Alpha
Classifier: Intended Audience :: Developers
Classifier: License :: OSI Approved :: ISC License (ISCL)
Classifier: Natural Language :: English
Classifier: Programming Language :: Python :: 3
Classifier: Programming Language :: Python :: 3.3
Classifier: Programming Language :: Python :: 3.4
Classifier: Programming Language :: Python :: 3.5
